MHcut/MHcut.py
MHcut/MHcut_old.py
MHcut/__init__.py
MHcut/cartoon.py
MHcut/flanks.py
MHcut/pam_utils.py
MHcut/run_mhcut.py
MHcut/seq_utils.py
MHcut/variant.py
MHcut/inDelphi/__init__.py
MHcut/inDelphi/inDelphi.py
tests/__init__.py
tests/test_mhcut.py
MHcut-1.0.0.dist-info/LICENSE
MHcut-1.0.0.dist-info/METADATA
MHcut-1.0.0.dist-info/WHEEL
MHcut-1.0.0.dist-info/entry_points.txt
MHcut-1.0.0.dist-info/top_level.txt
MHcut-1.0.0.dist-info/RECORD
